{"cameraMode":{"drawMode":0,"name":"Shaded","section":"Shading Mode"},"sceneLighting":false,"audioPlay":false,"sceneViewState":{"m_AlwaysRefresh":false,"showFog":true,"showSkybox":false,"showFlares":true,"showImageEffects":true,"showParticleSystems":true,"showVisualEffectGraphs":true,"m_FxEnabled":true},"in2DMode":false,"pivot":{"x":-3.0759496688842775,"y":2.6773128509521486,"z":7.498168468475342},"rotation":{"x":0.1086578443646431,"y":-0.7122521996498108,"z":0.1131165474653244,"w":0.6841771006584168},"size":2.014427900314331,"orthographic":false}